noscope/__init__.py
noscope-1.0.1.dist-info/LICENSE
noscope-1.0.1.dist-info/METADATA
noscope-1.0.1.dist-info/WHEEL
noscope-1.0.1.dist-info/top_level.txt
noscope-1.0.1.dist-info/RECORD
