Metadata-Version: 2.1
Name: noscope
Version: 1.0.1
Summary: Python scope snapshot tool
Home-page: https://github.com/theradius/noscope
Author: theradius
License: UNKNOWN
Keywords: Python scope snapshot tool
Platform: UNKNOWN
Classifier: Development Status :: 3 - Alpha
Classifier: Intended Audience :: Developers
Classifier: License :: OSI Approved :: GNU Lesser General Public License v3 (LGPLv3)
Classifier: Programming Language :: Python :: 3
License-File: LICENSE
